datatools/__init__.py
datatools/cli.py
datatools/core.py
datatools/djson2geojson.py
datatools/io.py
datatools/join.py
datatools/stats.py
datatools-0.1.3.data/scripts/body
datatools-0.1.3.data/scripts/cols
datatools-0.1.3.data/scripts/header
datatools-0.1.3.dist-info/DESCRIPTION.rst
datatools-0.1.3.dist-info/METADATA
datatools-0.1.3.dist-info/RECORD
datatools-0.1.3.dist-info/WHEEL
datatools-0.1.3.dist-info/entry_points.txt
datatools-0.1.3.dist-info/metadata.json
datatools-0.1.3.dist-info/pbr.json
datatools-0.1.3.dist-info/top_level.txt
