Metadata-Version: 2.0
Name: datatools
Version: 0.1.3
Summary: Data Tools
Home-page: http://github.com/themiurgo/datatools
Author: Antonio Lima
Author-email: anto87@gmail.com
License: MIT
Platform: UNKNOWN
Requires-Dist: click
Requires-Dist: numpy
Requires-Dist: scipy
Requires-Dist: six
Requires-Dist: toolz
